{
  "model": "FoNDUE-GD_v2_fr",
  "editeur": "kraken",
  "modele_type": "libre",
  "image": "images\\AN-284AP-4-doss 11_page_12.png",
  "result": "R.\npreurbate\nbaque dropb garantre noy mere dons ee la mélice ctanel\nici piné losoine et vour toure à coups Mrubleffio. poablic\nvon eux grad peus eavre, il fatroit aux borbes de\nl'effociantion, por fodon tsonquilleoun à leut Ddevas,\nà lus ploinis perticulins, il ler fattoin dux fouaitios on\nbonon posan, voulart, maueda bn 1esableffont eivil\nel ler failloie des hones fort, e centions por eftres lapertion\nde lo vilonte rrde la deision des1\nGir aux citoyes a farrais tou, cor tou sor de la\nles tumous voulant, ils les vo chriy, con pour ldt\nrpoiiatt publenon\ndes houes executer\nil sem quedx les chisflo, le sone\nainsi le povire rete da taucher quellique je fse pr\nlous vyste maitus\nrpprantes. et telle so l desoi, pourd de ladifrée du\nil non favn un foste d'executiin, y\nCorpriy l'orre par reprseitation connion jour eplats.–\nyoiro. epeleth\nCe jou les tetoges qui forrciffue les dex cloffres d'horry,\nde livoesonr dire l'orgeu\ndestree a les entrater\nu e se\nl'instevitioin livile facilite l forrentr de 1\n1\net\npu le i\nl'instonctio ititerd cete des 1\net les taurex pess pretory doree d'aepe\nc\nARCHIVES\nTATIONALES",
  "timestamp": "2025-02-21T15:34:42.154147",
  "model_info": {
    "path": "kraken_models\\FoNDUE-GD_v2_fr.mlmodel"
  },
  "usage": {},
  "latency": 61.78523635864258
}