{
  "model": "ManuMcFondue",
  "editeur": "kraken",
  "modele_type": "libre",
  "image": "images\\AN-284AP-4-doss 14_page_9.png",
  "result": "en Celod, p. ae Janroy ster de votre eavy\not je croy jr vins ſerte, ur pertropp\nabstraeboo de nole ster aelvol, se\ndes danposs ge lemeareem eb tontes\n1rstj.\nV vslpon\nls piucup, cols la poffisent pos. on\npere etr aristocrabe e ls avoent. Ar\nConaqeren tena te ne roffarcrouut\n Iaoo teel de tette boucbe.—\nrankiavel congullerot de profiser\nla mealler docttior, de de proneter.\ndre,\nleor te quon ve\nte obdctrot\n5:  rgallae de cett demorch\npouvoit eter dioijcon chz laneua\naarofener\nss propes porey\ndevence ansi le enentr ou d. enveya\ntrop faciemen e de La doctrre\nen ds js prouosts dle la veelle.\n1.slycon\nRRCRINE.\nil e sopt pos de prraipes, on d\nCoayaeney il at yvortioa e mwald\nvoe macheur soaald tapeble de produr-",
  "timestamp": "2025-02-21T16:14:32.031932",
  "model_info": {
    "path": "kraken_models\\ManuMcFondue.mlmodel"
  },
  "usage": {},
  "latency": 53.834537744522095
}